serverRoberta/__init__.py
serverRoberta/config.ini
serverRoberta/datos.py
serverRoberta/encrypt.py
serverRoberta/robertaModel.py
serverRoberta/roberta_pb2.py
serverRoberta/roberta_pb2_grpc.py
serverRoberta/server.py
server_roberta-0.4.4.data/data/serverRoberta/config.ini
server_roberta-0.4.4.dist-info/METADATA
server_roberta-0.4.4.dist-info/WHEEL
server_roberta-0.4.4.dist-info/entry_points.txt
server_roberta-0.4.4.dist-info/top_level.txt
server_roberta-0.4.4.dist-info/RECORD
